burr/__init__.py
burr/log_setup.py
burr/py.typed
burr/system.py
burr/telemetry.py
burr/test_tracing.py
burr/version.py
burr/cli/__init__.py
burr/cli/__main__.py
burr/cli/demo_data.py
burr/common/__init__.py
burr/common/async_utils.py
burr/common/types.py
burr/core/__init__.py
burr/core/action.py
burr/core/application.py
burr/core/graph.py
burr/core/implementations.py
burr/core/parallelism.py
burr/core/persistence.py
burr/core/serde.py
burr/core/state.py
burr/core/typing.py
burr/core/validation.py
burr/examples/__init__.py
burr/examples/validate_examples.py
burr/examples/adaptive-crag/__init__.py
burr/examples/adaptive-crag/application.py
burr/examples/conversational-rag/__init__.py
burr/examples/conversational-rag/graph_db_example/application.py
burr/examples/conversational-rag/graph_db_example/graph_schema.py
burr/examples/conversational-rag/graph_db_example/hamilton_ingest.py
burr/examples/conversational-rag/graph_db_example/ingest_fighters.py
burr/examples/conversational-rag/graph_db_example/ingest_fights.py
burr/examples/conversational-rag/graph_db_example/utils.py
burr/examples/conversational-rag/simple_example/__init__.py
burr/examples/conversational-rag/simple_example/application.py
burr/examples/custom-serde/__init__.py
burr/examples/custom-serde/application.py
burr/examples/custom-serde/run.py
burr/examples/deep-researcher/__init__.py
burr/examples/deep-researcher/application.py
burr/examples/deep-researcher/prompts.py
burr/examples/deep-researcher/server.py
burr/examples/deep-researcher/utils.py
burr/examples/deployment/aws/lambda/app/__init__.py
burr/examples/deployment/aws/lambda/app/counter_app.py
burr/examples/deployment/aws/lambda/app/lambda_handler.py
burr/examples/email-assistant/__init__.py
burr/examples/email-assistant/application.py
burr/examples/email-assistant/server.py
burr/examples/fastapi/__init__.py
burr/examples/fastapi/application.py
burr/examples/fastapi/server.py
burr/examples/hamilton-integration/__init__.py
burr-0.40.2.dist-info/licenses/LICENSE
burr-0.40.2.dist-info/METADATA
burr-0.40.2.dist-info/WHEEL
burr-0.40.2.dist-info/entry_points.txt
burr-0.40.2.dist-info/top_level.txt
burr-0.40.2.dist-info/RECORD
