Metadata-Version: 2.4
Name: burr
Version: 0.40.2
Summary: A state machine for data projects
Author-email: Elijah ben Izzy <elijah@dagworks.io>, Stefan Krawczyk <stefan@dagworks.io>
Maintainer-email: Elijah ben Izzy <elijah@dagworks.io>, Stefan Krawczyk <stefan@dagworks.io>
Project-URL: Homepage, https://github.com/dagworks-inc/burr
Project-URL: Documentation, https://github.com/dagworks-inc/burr
Project-URL: Repository, https://github.com/dagworks-inc/burr
Project-URL: Bug Tracker, https://github.com/dagworks-inc/burr
Keywords: mlops,data,state-machine,llmops
Classifier: Development Status :: 4 - Beta
Classifier: Programming Language :: Python
Requires-Python: >=3.9
License-File: LICENSE
Provides-Extra: streamlit
Requires-Dist: streamlit; extra == "streamlit"
Requires-Dist: graphviz; extra == "streamlit"
Requires-Dist: matplotlib; extra == "streamlit"
Requires-Dist: sf-hamilton; extra == "streamlit"
Provides-Extra: hamilton
Requires-Dist: sf-hamilton; extra == "hamilton"
Provides-Extra: graphviz
Requires-Dist: graphviz; extra == "graphviz"
Provides-Extra: aiosqlite
Requires-Dist: aiosqlite; extra == "aiosqlite"
Provides-Extra: asyncpg
Requires-Dist: asyncpg; extra == "asyncpg"
Provides-Extra: postgresql
Requires-Dist: psycopg2-binary; extra == "postgresql"
Provides-Extra: psycopg2
Requires-Dist: psycopg2-binary; extra == "psycopg2"
Provides-Extra: pymongo
Requires-Dist: pymongo; extra == "pymongo"
Provides-Extra: redis
Requires-Dist: redis; extra == "redis"
Provides-Extra: tests
Requires-Dist: pytest; extra == "tests"
Requires-Dist: pytest-asyncio; extra == "tests"
Requires-Dist: burr[hamilton]; extra == "tests"
Requires-Dist: burr[hamilton]; extra == "tests"
Requires-Dist: langchain_core; extra == "tests"
Requires-Dist: langchain_community; extra == "tests"
Requires-Dist: pandas; extra == "tests"
Requires-Dist: pydantic[email]; extra == "tests"
Requires-Dist: pyarrow; extra == "tests"
Requires-Dist: burr[aiosqlite]; extra == "tests"
Requires-Dist: burr[asyncpg]; extra == "tests"
Requires-Dist: burr[psycopg2]; extra == "tests"
Requires-Dist: burr[pymongo]; extra == "tests"
Requires-Dist: burr[redis]; extra == "tests"
Requires-Dist: burr[opentelemetry]; extra == "tests"
Requires-Dist: burr[haystack]; extra == "tests"
Requires-Dist: burr[ray]; extra == "tests"
Provides-Extra: documentation
Requires-Dist: burr[tests]; extra == "documentation"
Requires-Dist: sphinx; extra == "documentation"
Requires-Dist: sphinx-autobuild; extra == "documentation"
Requires-Dist: myst-nb; extra == "documentation"
Requires-Dist: furo; extra == "documentation"
Requires-Dist: sphinx-sitemap; extra == "documentation"
Requires-Dist: sphinx-toolbox; extra == "documentation"
Requires-Dist: burr[aiosqlite]; extra == "documentation"
Requires-Dist: burr[asyncpg]; extra == "documentation"
Requires-Dist: burr[psycopg2]; extra == "documentation"
Requires-Dist: burr[pymongo]; extra == "documentation"
Requires-Dist: burr[redis]; extra == "documentation"
Requires-Dist: burr[ray]; extra == "documentation"
Requires-Dist: sphinxcontrib-googleanalytics; extra == "documentation"
Provides-Extra: tracking-client
Requires-Dist: pydantic>1; extra == "tracking-client"
Provides-Extra: tracking-client-s3
Requires-Dist: burr[tracking-client]; extra == "tracking-client-s3"
Requires-Dist: boto3; extra == "tracking-client-s3"
Provides-Extra: tracking-server-s3
Requires-Dist: aerich; extra == "tracking-server-s3"
Requires-Dist: aiobotocore; extra == "tracking-server-s3"
Requires-Dist: fastapi; extra == "tracking-server-s3"
Requires-Dist: tortoise-orm[accel,asyncmy]; extra == "tracking-server-s3"
Requires-Dist: burr[tracking-server]; extra == "tracking-server-s3"
Requires-Dist: typing-inspect; extra == "tracking-server-s3"
Provides-Extra: tracking-server
Requires-Dist: click; extra == "tracking-server"
Requires-Dist: fastapi; extra == "tracking-server"
Requires-Dist: uvicorn; extra == "tracking-server"
Requires-Dist: pydantic; extra == "tracking-server"
Requires-Dist: pydantic-settings; extra == "tracking-server"
Requires-Dist: fastapi-pagination; extra == "tracking-server"
Requires-Dist: fastapi-utils; extra == "tracking-server"
Requires-Dist: aiofiles; extra == "tracking-server"
Requires-Dist: requests; extra == "tracking-server"
Requires-Dist: jinja2; extra == "tracking-server"
Requires-Dist: openai; extra == "tracking-server"
Requires-Dist: typing-inspect; extra == "tracking-server"
Provides-Extra: pydantic
Requires-Dist: pydantic; extra == "pydantic"
Provides-Extra: haystack
Requires-Dist: haystack-ai; extra == "haystack"
Provides-Extra: cli
Requires-Dist: loguru; extra == "cli"
Requires-Dist: click; extra == "cli"
Requires-Dist: requests; extra == "cli"
Provides-Extra: tracking
Requires-Dist: burr[tracking-client]; extra == "tracking"
Requires-Dist: burr[tracking-server]; extra == "tracking"
Provides-Extra: learn
Requires-Dist: burr[cli,graphviz,hamilton,inappexamples,streamlit,tracking]; extra == "learn"
Provides-Extra: start
Requires-Dist: burr[learn]; extra == "start"
Provides-Extra: inappexamples
Requires-Dist: opentelemetry-api; extra == "inappexamples"
Requires-Dist: opentelemetry-sdk; extra == "inappexamples"
Requires-Dist: opentelemetry-instrumentation-openai; extra == "inappexamples"
Requires-Dist: tavily-python; extra == "inappexamples"
Provides-Extra: examples
Requires-Dist: langchain; extra == "examples"
Requires-Dist: langchain-community; extra == "examples"
Requires-Dist: langchain-openai; extra == "examples"
Requires-Dist: burr[inappexamples]; extra == "examples"
Provides-Extra: developer
Requires-Dist: burr[streamlit]; extra == "developer"
Requires-Dist: burr[graphviz]; extra == "developer"
Requires-Dist: burr[tracking]; extra == "developer"
Requires-Dist: burr[tests]; extra == "developer"
Requires-Dist: burr[documentation]; extra == "developer"
Requires-Dist: burr[bloat]; extra == "developer"
Requires-Dist: build; extra == "developer"
Requires-Dist: twine; extra == "developer"
Requires-Dist: pre-commit; extra == "developer"
Provides-Extra: opentelemetry
Requires-Dist: opentelemetry-api; extra == "opentelemetry"
Requires-Dist: opentelemetry-sdk; extra == "opentelemetry"
Provides-Extra: ray
Requires-Dist: ray[default]; extra == "ray"
Dynamic: license-file
